epr.py
epr_reader-2.4.14.dist-info/entry_points.txt
epr_reader-2.4.14.dist-info/LICENSE
epr_reader-2.4.14.dist-info/WHEEL
epr_reader-2.4.14.dist-info/METADATA
epr_reader-2.4.14.dist-info/RECORD
