Metadata-Version: 2.1
Name: epr-reader
Version: 2.4.14
Summary: CLI Ebook Reader
License: MIT
Keywords: EPUB,EPUB3,CLI,TUI,Terminal,Reader
Author: Benawi Adha
Author-email: benawiadha@gmail.com
Requires-Python: >=3.7,<4.0
Classifier: License :: OSI Approved :: MIT License
Classifier: Programming Language :: Python :: 3
Classifier: Programming Language :: Python :: 3.7
Classifier: Programming Language :: Python :: 3.8
Classifier: Programming Language :: Python :: 3.9
Classifier: Programming Language :: Python :: 3.10
Requires-Dist: windows-curses; platform_system == "Windows"
